cirr/__init__.py
cirr/skeleton.py
cirr-0.0.1.dist-info/AUTHORS.rst
cirr-0.0.1.dist-info/LICENSE.txt
cirr-0.0.1.dist-info/METADATA
cirr-0.0.1.dist-info/WHEEL
cirr-0.0.1.dist-info/entry_points.txt
cirr-0.0.1.dist-info/top_level.txt
cirr-0.0.1.dist-info/RECORD
