Metadata-Version: 2.1
Name: cirr
Version: 0.0.1
Summary: Add a short description here!
Home-page: https://github.com/pyscaffold/pyscaffold/
Author: LaurenÈ›iu Andronache
Author-email: laurentiu.andronache@trailung.ro
License: mit
Project-URL: Documentation, https://pyscaffold.org/
Platform: any
Classifier: Development Status :: 4 - Beta
Classifier: Programming Language :: Python
Provides-Extra: testing
Requires-Dist: pytest ; extra == 'testing'
Requires-Dist: pytest-cov ; extra == 'testing'
